deepcoin/__init__.py
deepcoin/auth.py
deepcoin/base_client.py
deepcoin/client.py
deepcoin/exceptions.py
deepcoin/utils/logger.py
deepcoin/ws/__init__.py
deepcoin/ws/connection.py
deepcoin/ws/dispatcher.py
deepcoin/ws/enums.py
deepcoin/ws/exceptions.py
deepcoin/ws/manager.py
deepcoin/ws/stream.py
deepcoin/ws/topics.py
python_deepcoin-0.2.1.dist-info/licenses/LICENSE
python_deepcoin-0.2.1.dist-info/METADATA
python_deepcoin-0.2.1.dist-info/WHEEL
python_deepcoin-0.2.1.dist-info/top_level.txt
python_deepcoin-0.2.1.dist-info/RECORD
