Metadata-Version: 2.4
Name: python-deepcoin
Version: 0.2.1
Summary: Unofficial Python wrapper for the DeepCoin API (REST + WebSocket)
Author-email: parker1019 <parker178912@gmail.com>
License: MIT
Project-URL: Homepage, https://github.com/parker1019/python-deepcoin
Project-URL: Documentation, https://www.deepcoin.com/docs/authentication
Requires-Python: >=3.13
License-File: LICENSE
Requires-Dist: colorlog>=6.9.0
Requires-Dist: python-dotenv>=1.1.1
Requires-Dist: requests>=2.32.4
Requires-Dist: websocket-client>=1.8.0
Dynamic: license-file
